{
  "defaultEntryPoint": "index.html",
  "namespace": "EquipmentRental",
  "menuEntries": [
    {
      "label": "Einstellungen",
      "menu": "settings/orders/EquipmentRental",
      "urlKey": "settings",
      "entryPoint": "index.html#/plugin/settings"
    },
    {
      "label": "Geräteübersicht",
      "menu": "settings/orders/EquipmentRental",
      "urlKey": "overview",
      "entryPoint": "index.html#/plugin/overview"
    },
    {
      "label": "Verleihübersicht",
      "menu": "settings/orders/EquipmentRental",
      "urlKey": "manage",
      "entryPoint": "index.html#/plugin/manage"
    }
  ]
}
